regex_replacer/__init__.py
regex_replacer/regex_replacer.cpython-38-x86_64-linux-gnu.so
regex_replacer-0.1.4.dist-info/LICENSE
regex_replacer-0.1.4.dist-info/METADATA
regex_replacer-0.1.4.dist-info/WHEEL
regex_replacer-0.1.4.dist-info/top_level.txt
regex_replacer-0.1.4.dist-info/RECORD
