Metadata-Version: 2.1
Name: regex_replacer
Version: 0.1.4
Summary: Simple class for replace test with regex. Support scikit-learn transformer interface.
Author-email: GAlexander <g.alexander.box@gmail.com>
Project-URL: Homepage, https://github.com/g-alexander/regex_replacer
Project-URL: Bug Tracker, https://github.com/g-alexander/regex_replacer/issues
Classifier: Programming Language :: Python :: 3
Classifier: License :: OSI Approved :: MIT License
Classifier: Operating System :: POSIX :: Linux
Requires-Python: <3.14.0,>=3.8
License-File: LICENSE
Requires-Dist: scikit-learn
